{
    "{Nex.api}": {
        "Facebook": {
            "app": {
                "cookie": "1"
            },
            "login_params": {
                "canvas": "0"
            }
        },

        "Google": {
            "recaptcha2": {
                "site_key": null,
                "secret": null
            }
        },

        "Paypal": {
            "host": "www.paypal.com",
            "sandbox_host": "www.sandbox.paypal.com",
            "sandbox": "1",
            "use_ssl": "1"
        },

        "CanadaPost": {
            "sandbox": "1",
            "app": {
                "username": null,
                "password": null
            }
        },

        "Eckinox": {
            "auth": {},
            "useragent": "PHP-NEX-API/1.0.0",
            "path": {
                "url": "https://api.eckinox.net/",
                "base": "rest",
                "facebook": "facebook",
                "domain" : "domain",
                "image": "image"
            }
        }
    }
}
